pyVPRM/VPRM.py
pyVPRM/__init__.py
pyVPRM/flux_tower_libs/FFP_footprint_class.py
pyVPRM/flux_tower_libs/KM_footprint_class.py
pyVPRM/flux_tower_libs/__init__.py
pyVPRM/flux_tower_libs/base_footprint_class.py
pyVPRM/flux_tower_libs/flux_tower_class.py
pyVPRM/lib/__init__.py
pyVPRM/lib/downmodis.py
pyVPRM/lib/fancy_plot.py
pyVPRM/lib/functions.py
pyVPRM/lib/reproject_fiona.py
pyVPRM/lib/fluxnet_info/fluxnet_sites.pkl
pyVPRM/lib/fluxnet_info/site_infos.txt
pyVPRM/meteorologies/__init__.py
pyVPRM/meteorologies/era5_class_dkrz.py
pyVPRM/meteorologies/era5_class_draft.py
pyVPRM/meteorologies/era5_land_destinE.py
pyVPRM/meteorologies/era5_monthly_xr.py
pyVPRM/meteorologies/met_base_class.py
pyVPRM/meteorologies/met_local_measurement.py
pyVPRM/sat_managers/__init__.py
pyVPRM/sat_managers/base_manager.py
pyVPRM/sat_managers/city.py
pyVPRM/sat_managers/copernicus.py
pyVPRM/sat_managers/esa_world_cover.py
pyVPRM/sat_managers/lads_downloader.py
pyVPRM/sat_managers/mapbiomas.py
pyVPRM/sat_managers/modis.py
pyVPRM/sat_managers/proba_v.py
pyVPRM/sat_managers/sentinel2.py
pyVPRM/sat_managers/synmap.py
pyVPRM/sat_managers/viirs.py
pyVPRM/sat_managers/viirs09ga.py
pyVPRM/vprm_configs/__init__.py
pyVPRM/vprm_configs/copernicus_land_cover.yaml
pyVPRM/vprm_configs/esa_world_cover.yaml
pyVPRM/vprm_configs/synmap.yaml
pyVPRM/vprm_models/__init__.py
pyVPRM/vprm_models/vprm_base_model.py
pyVPRM/vprm_models/vprm_base_model_no_xeric.py
pyVPRM/vprm_models/vprm_modified_model.py
pyVPRM/vprm_models/vprm_nn_model.py
pyVPRM/vprm_models/model_params/__init__.py
pyvprm-5.3.dist-info/licenses/LICENSE
pyvprm-5.3.dist-info/METADATA
pyvprm-5.3.dist-info/WHEEL
pyvprm-5.3.dist-info/top_level.txt
pyvprm-5.3.dist-info/RECORD
