Metadata-Version: 2.4
Name: pyVPRM
Version: 5.3
Summary: Vegetation Photosynthesis and Respiration Model
Home-page: https://github.com/tglauch/pyVPRM/
Author: Theo Glauch
Author-email: theo.glauch@drl.de
License: MIT
Keywords: CO2 Biosphere Atmosphere Physics VPRM
Classifier: Development Status :: 5 - Production/Stable
Classifier: Environment :: Console
Classifier: Intended Audience :: Science/Research
Classifier: License :: OSI Approved :: MIT License
Classifier: Topic :: Scientific/Engineering :: Atmospheric Science
Classifier: Programming Language :: Python :: 3.14
License-File: LICENSE
Requires-Dist: numpy
Requires-Dist: scipy
Requires-Dist: xarray
Requires-Dist: xesmf
Requires-Dist: pyproj
Requires-Dist: joblib
Requires-Dist: uuid
Requires-Dist: pandas
Requires-Dist: astropy
Requires-Dist: pyyaml
Requires-Dist: rasterio
Requires-Dist: rioxarray
Requires-Dist: geopandas
Requires-Dist: h5py
Requires-Dist: pytz
Requires-Dist: tzwhere
Requires-Dist: timezonefinder
Requires-Dist: pygrib
Requires-Dist: matplotlib
Requires-Dist: lxml
Requires-Dist: requests
Requires-Dist: statsmodels
Requires-Dist: loguru
Requires-Dist: fiona
Requires-Dist: pykalman
Dynamic: author
Dynamic: author-email
Dynamic: classifier
Dynamic: description
Dynamic: home-page
Dynamic: keywords
Dynamic: license
Dynamic: license-file
Dynamic: requires-dist
Dynamic: summary
